AUTHORS
LICENSE
MANIFEST.in
README.rst
setup.py
src/serafin/__init__.py
src/serafin/context.py
src/serafin/fieldspec.py
src/serafin/serializer.py
src/serafin/serializers.py
src/serafin/util.py
src/serafin.egg-info/PKG-INFO
src/serafin.egg-info/SOURCES.txt
src/serafin.egg-info/dependency_links.txt
src/serafin.egg-info/requires.txt
src/serafin.egg-info/top_level.txt