Metadata-Version: 1.1
Name: serafin
Version: 0.12
Summary: Python library that implementing selective serialization
Home-page: http://github.com/novopl/serafin
Author: Mateusz 'novo' Klos
Author-email: novopl@gmail.com
License: MIT
Keywords: serafin serialize serialization json config
Platform: UNKNOWN
Classifier: Development Status :: 4 - Beta
Classifier: Topic :: Utilities
Classifier: Intended Audience :: Developers
Classifier: Programming Language :: Python
Classifier: License :: OSI Approved :: MIT License
